README.md
setup.py
chokola/__init__.py
chokola/formatter.py
chokola/markdown.py
chokola/renderer.py
chokola/table.py
chokola.egg-info/PKG-INFO
chokola.egg-info/SOURCES.txt
chokola.egg-info/dependency_links.txt
chokola.egg-info/requires.txt
chokola.egg-info/top_level.txt
scripts/chokola