Metadata-Version: 1.0
Name: chokola
Version: 0.2.1
Summary: YAML to HTML Table
Home-page: https://gitlab.com/chokola/chokola
Author: Noel Martignoni
Author-email: noel@martignoni.fr
License: UNKNOWN
Platform: UNKNOWN
